micrograd_utils/__init__.py
micrograd_utils/utils.py
micrograd_utils-0.0.5.dist-info/LICENSE
micrograd_utils-0.0.5.dist-info/METADATA
micrograd_utils-0.0.5.dist-info/WHEEL
micrograd_utils-0.0.5.dist-info/top_level.txt
micrograd_utils-0.0.5.dist-info/RECORD
