Metadata-Version: 2.1
Name: micrograd-utils
Version: 0.0.5
Summary: utils for micrograd
Author-email: Valerio Iacobucci <valerio@valerioiacobucci.com>
Project-URL: Homepage, https://github.com/iacobucci/micrograd-utils
Classifier: Programming Language :: Python :: 3
Classifier: License :: OSI Approved :: MIT License
Classifier: Operating System :: OS Independent
Requires-Python: >=3.7
License-File: LICENSE
